README.md
setup.py
Terry_toolkit/CxExtractor.py
Terry_toolkit/SearchBaidu.py
Terry_toolkit/TextRank4ZH.py
Terry_toolkit/__init__.py
Terry_toolkit/bootstrap.py
Terry_toolkit/crawler_baidu.py
Terry_toolkit/csv.py
Terry_toolkit/db.py
Terry_toolkit/dict_get.py
Terry_toolkit/file.py
Terry_toolkit/ie.py
Terry_toolkit/list.py
Terry_toolkit/ner.py
Terry_toolkit/pkl.py
Terry_toolkit/resources.py
Terry_toolkit/search.py
Terry_toolkit/sentence_parser.py
Terry_toolkit/text.py
Terry_toolkit/tjson.py
Terry_toolkit/triple_extraction.py
Terry_toolkit/turl.py
Terry_toolkit.egg-info/PKG-INFO
Terry_toolkit.egg-info/SOURCES.txt
Terry_toolkit.egg-info/dependency_links.txt
Terry_toolkit.egg-info/requires.txt
Terry_toolkit.egg-info/top_level.txt